<?xml version="1.0" encoding="utf-8" ?>
<Patch>


	<Operation Class="PatchOperationFindMod">
		<mods>
			<li>ReSplice: Charmweavers</li>
		</mods>
		<match Class="PatchOperationAdd">
			<xpath>Defs/MemeDef[defName="RS_LoveLusting"]</xpath>
			<value>
				<requireOne>
					<li>
						<li>NikolaisIdeology_Aphrodors_Elevated</li>
						<li>NikolaisIdeology_Aphrodors_Sacred</li>
					</li>
					<li>
						<li>NikolaisIdeology_Neutors_Reviled</li>
					</li>
					<li>
						<li>NikolaisIdeology_Intimacy_High</li>
					</li>
				</requireOne>
				<exclusionTags>
					<li>NoLovelusting</li>
				</exclusionTags>
			</value>
		</match>
	</Operation>
	<Operation Class="PatchOperationFindMod">
		<mods>
			<li>Alpha Memes</li>
		</mods>
		<match Class="PatchOperationAdd">
			<xpath>Defs/PreceptDef[defName="AM_LovinFrequency_Exuberant"]/associatedMemes</xpath>
			<value>
				<li>NikolaisIdeology_Aphroditic</li>
			</value>
		</match>
	</Operation>
	<Operation Class="PatchOperationFindMod">
		<mods>
			<li>Alpha Memes</li>
		</mods>
		<match Class="PatchOperationAdd">
			<xpath>Defs/PreceptDef[defName="AM_LovinFrequency_Increased"]/associatedMemes</xpath>
			<value>
				<li>NikolaisIdeology_Aphroditic</li>
			</value>
		</match>
	</Operation>
	<Operation Class="PatchOperationFindMod">
		<mods>
			<li>Alpha Memes</li>
		</mods>
		<match Class="PatchOperationAdd">
			<xpath>Defs/PreceptDef[defName="AM_LovinFrequency_Decreased"]/associatedMemes</xpath>
			<value>
				<li>NikolaisIdeology_Chastity</li>
			</value>
		</match>
	</Operation>
	<Operation Class="PatchOperationFindMod">
		<mods>
			<li>Alpha Memes</li>
		</mods>
		<match Class="PatchOperationAdd">
			<xpath>Defs/PreceptDef[defName="AM_LovinFrequency_Exuberant"]/requiredMemes</xpath>
			<value>
				<li>NikolaisIdeology_Aphroditic</li>
			</value>
		</match>
	</Operation>
	<Operation Class="PatchOperationFindMod">
		<mods>
			<li>Alpha Memes</li>
		</mods>
		<match Class="PatchOperationAdd">
				<xpath>Defs/MemeDef[defName="AM_Monastic]</xpath>
				<value>
					<exclusionTags>
						<li>LustVsChaste</li>
						<li>MonasticVsPreachingZealotTypeShit</li>
					</exclusionTags>
				</value>
			</match>
	</Operation>
	<Operation Class="PatchOperationFindMod">
		<mods>
			<li>Vanilla Ideology Expanded: Memes and Structures</li>
		</mods>
		<match Class="PatchOperationAdd">
			<xpath>Defs/PreceptDef[defName="VME_RecreationLoved"]/associatedMemes</xpath>
			<value>
				<li>NikolaisIdeology_Aphroditic</li>
			</value>
		</match>
	</Operation>
	<Operation Class="PatchOperationFindMod">
		<mods>
			<li>Vanilla Ideology Expanded: Memes and Structures</li>
		</mods>
		<match Class="PatchOperationAdd">
			<xpath>Defs/MemeDef[defName="VME_HolyDiseases"]</xpath>
			<value>
				<exclusionTags>
					<li>BeautyVsUgliness</li>
					<li>PurityVsDirt</li>
				</exclusionTags>
			</value>
		</match>
		</Operation>
	<Operation Class="PatchOperationFindMod">
		<mods>
			<li>Vanilla Ideology Expanded: Memes and Structures</li>
		</mods>
		<match Class="PatchOperationAdd">
			<xpath>Defs/MemeDef[defName="VME_Scrapper"]</xpath>
			<value>
				<exclusionTags>
					<li>BeautyVsUgliness</li>
					<li>PurityVsDirt</li>
				</exclusionTags>
			</value>
		</match>
	</Operation>

</Patch>